linkstation/__init__.py
linkstation/const.py
linkstation/linkstation.py
linkstation-0.0.11.dist-info/LICENSE
linkstation-0.0.11.dist-info/METADATA
linkstation-0.0.11.dist-info/WHEEL
linkstation-0.0.11.dist-info/top_level.txt
linkstation-0.0.11.dist-info/RECORD
