Metadata-Version: 2.1
Name: linkstation
Version: 0.0.11
Summary: A python client for Buffalo LinkStation
Home-page: https://github.com/iKaew/linkstation
Author: Teesit Eadthongsai
Author-email: teesite-pypi@outlook.com
License: UNKNOWN
Project-URL: Bug Tracker, https://github.com/iKaew/linkstation/issues
Platform: UNKNOWN
Classifier: Programming Language :: Python :: 3
Classifier: License :: OSI Approved :: MIT License
Classifier: Operating System :: OS Independent
Requires-Python: >=3.9
License-File: LICENSE
